setup.py
gtycwifi/__init__.py
gtycwifi/_wifiutil_linux.py
gtycwifi/_wifiutil_win.py
gtycwifi/const.py
gtycwifi/iface.py
gtycwifi/profile.py
gtycwifi/wifi.py
gtycwifi.egg-info/PKG-INFO
gtycwifi.egg-info/SOURCES.txt
gtycwifi.egg-info/dependency_links.txt
gtycwifi.egg-info/top_level.txt