Metadata-Version: 1.0
Name: gtycwifi
Version: 1.1.13
Summary: A LIB
Home-page: UNKNOWN
Author: GTYC
Author-email: UNKNOWN
License: GTYC License
Keywords: gtycwifi
Platform: any
